pttools/__init__.py
pttools/logging.py
pttools/type_hints.py
pttools/analysis/__init__.py
pttools/analysis/bubble_grid.py
pttools/analysis/colormap.py
pttools/analysis/entropy.py
pttools/analysis/g_cs2.py
pttools/analysis/parallel.py
pttools/analysis/plot_bubble.py
pttools/analysis/plot_bubbles.py
pttools/analysis/plot_chapman_jouguet.py
pttools/analysis/plot_delta_theta.py
pttools/analysis/plot_entropy.py
pttools/analysis/plot_entropy_grid.py
pttools/analysis/plot_fluid_shell_3d.py
pttools/analysis/plot_fluid_shell_bag.py
pttools/analysis/plot_fluid_shells_bag.py
pttools/analysis/plot_model.py
pttools/analysis/plot_models.py
pttools/analysis/plot_plotly.py
pttools/analysis/plot_spectra.py
pttools/analysis/plot_spectrum.py
pttools/analysis/plot_thermomodels.py
pttools/analysis/plot_vw_alpha.py
pttools/analysis/plot_xiv_plane.py
pttools/analysis/utils.py
pttools/bubble/__init__.py
pttools/bubble/alpha.py
pttools/bubble/approx.py
pttools/bubble/bag.py
pttools/bubble/boundary.py
pttools/bubble/bubble.py
pttools/bubble/bubble_quantities.py
pttools/bubble/chapman_jouguet.py
pttools/bubble/check.py
pttools/bubble/const.py
pttools/bubble/fluid.py
pttools/bubble/fluid_bag.py
pttools/bubble/fluid_reference.py
pttools/bubble/giese.py
pttools/bubble/integrate.py
pttools/bubble/ke_frac_approx.py
pttools/bubble/physical_params.py
pttools/bubble/props.py
pttools/bubble/quantities.py
pttools/bubble/relativity.py
pttools/bubble/shock.py
pttools/bubble/thermo.py
pttools/bubble/transition.py
pttools/bubble/trim.py
pttools/models/__init__.py
pttools/models/analytic.py
pttools/models/bag.py
pttools/models/base.py
pttools/models/const_cs.py
pttools/models/const_cs_thermo.py
pttools/models/full.py
pttools/models/giese_cubic.py
pttools/models/giese_twostep.py
pttools/models/model.py
pttools/models/sigmoid.py
pttools/models/sm.py
pttools/models/thermo.py
pttools/omgw0/__init__.py
pttools/omgw0/approx.py
pttools/omgw0/const.py
pttools/omgw0/noise.py
pttools/omgw0/omgw0_ssm.py
pttools_gw-0.9.0.dist-info/licenses/LICENSE
pttools_gw-0.9.0.dist-info/METADATA
pttools_gw-0.9.0.dist-info/WHEEL
pttools_gw-0.9.0.dist-info/top_level.txt
pttools_gw-0.9.0.dist-info/RECORD
