Metadata-Version: 2.4
Name: pttools-gw
Version: 0.9.0
Summary: PTtools simulation framework for phase transitions in the early universe
Author-email: Mark Hindmarsh <mark.hindmarsh@helsinki.fi>, Chloe Hopling <c.hopling@sussex.ac.uk>, Mika Mäki <mika.x.maki@helsinki.fi>
Maintainer-email: Mark Hindmarsh <mark.hindmarsh@helsinki.fi>, Mika Mäki <mika.x.maki@helsinki.fi>
License-Expression: MIT
Project-URL: documentation, https://pttools.readthedocs.io
Project-URL: repository, https://github.com/CFT-HY/pttools
Keywords: cosmology,phase transitions,gravitational waves,hydrodynamics,relativistic hydrodynamics,sound shell model
Classifier: Framework :: Matplotlib
Classifier: Intended Audience :: Developers
Classifier: Intended Audience :: Education
Classifier: Intended Audience :: Science/Research
Classifier: Operating System :: OS Independent
Classifier: Programming Language :: Python
Classifier: Programming Language :: Python :: 3.11
Classifier: Programming Language :: Python :: 3.12
Classifier: Programming Language :: Python :: 3.13
Classifier: Topic :: Scientific/Engineering
Classifier: Topic :: Scientific/Engineering :: Physics
Classifier: Topic :: Scientific/Engineering :: Visualization
Classifier: Topic :: Software Development :: Libraries
Requires-Python: >=3.11
License-File: LICENSE
Requires-Dist: h5py>=3.12.1
Requires-Dist: kaleido>=0.2.1
Requires-Dist: matplotlib>=3.9.2
Requires-Dist: numba>=0.60.0
Requires-Dist: numpy>=2.0.2
Requires-Dist: orjson>=3.10.12
Requires-Dist: plotly>=5.24.1
Requires-Dist: scipy>=1.14.1
Provides-Extra: numbalsoda
Requires-Dist: numbalsoda>=0.3.4; extra == "numbalsoda"
Provides-Extra: performance
Requires-Dist: icc-rt>=2019.0; platform_machine != "arm64" and extra == "performance"
Requires-Dist: intel-openmp>=2020.0.133; (sys_platform == "darwin" and platform_machine != "arm64") and extra == "performance"
Requires-Dist: tbb>=2021.10.0; platform_machine != "arm64" and extra == "performance"
Dynamic: license-file
